README
setup.py
django_jqtouch.egg-info/PKG-INFO
django_jqtouch.egg-info/SOURCES.txt
django_jqtouch.egg-info/dependency_links.txt
django_jqtouch.egg-info/not-zip-safe
django_jqtouch.egg-info/requires.txt
django_jqtouch.egg-info/top_level.txt
docs/CONTRIBUTORS
docs/HISTORY
docs/LICENSE
jqtouch/__init__.py
jqtouch/admin.py
jqtouch/exceptions.py
jqtouch/models.py
jqtouch/resolvers.py
jqtouch/settings.py
jqtouch/urls.py
jqtouch/views.py
jqtouch/templates/jqtouch/ajax.html
jqtouch/templates/jqtouch/base.html